{
    "message_size": 128,
    "n_runs": 10,
    "num_pairs": 16,
    "run0": {
        "pair0": {
            "client_recv_end": 1763930457104149184,
            "client_recv_start": 1763930457104148448,
            "client_trans_end": 1763930457104148160,
            "client_trans_start": 1763930457104147456,
            "server_recv_end": 1763930457104148256,
            "server_recv_start": 1763930457104147680,
            "server_trans_end": 1763930457104149184,
            "server_trans_start": 1763930457104148256
        },
        "pair1": {
            "client_recv_end": 1763930457104149184,
            "client_recv_start": 1763930457104148448,
            "client_trans_end": 1763930457104148160,
            "client_trans_start": 1763930457104147456,
            "server_recv_end": 1763930457104148256,
            "server_recv_start": 1763930457104147680,
            "server_trans_end": 1763930457104149184,
            "server_trans_start": 1763930457104148256
        },
        "pair10": {
            "client_recv_end": 1763930457104149184,
            "client_recv_start": 1763930457104148448,
            "client_trans_end": 1763930457104148160,
            "client_trans_start": 1763930457104147456,
            "server_recv_end": 1763930457104148256,
            "server_recv_start": 1763930457104147680,
            "server_trans_end": 1763930457104149184,
            "server_trans_start": 1763930457104148256
        },
        "pair11": {
            "client_recv_end": 1763930457104149184,
            "client_recv_start": 1763930457104148448,
            "client_trans_end": 1763930457104148160,
            "client_trans_start": 1763930457104147456,
            "server_recv_end": 1763930457104148256,
            "server_recv_start": 1763930457104147680,
            "server_trans_end": 1763930457104149184,
            "server_trans_start": 1763930457104148256
        },
        "pair12": {
            "client_recv_end": 1763930457104149184,
            "client_recv_start": 1763930457104148448,
            "client_trans_end": 1763930457104148160,
            "client_trans_start": 1763930457104147456,
            "server_recv_end": 1763930457104148256,
            "server_recv_start": 1763930457104147680,
            "server_trans_end": 1763930457104149184,
            "server_trans_start": 1763930457104148256
        },
        "pair13": {
            "client_recv_end": 1763930457104149184,
            "client_recv_start": 1763930457104148448,
            "client_trans_end": 1763930457104148160,
            "client_trans_start": 1763930457104147456,
            "server_recv_end": 1763930457104148256,
            "server_recv_start": 1763930457104147680,
            "server_trans_end": 1763930457104149184,
            "server_trans_start": 1763930457104148256
        },
        "pair14": {
            "client_recv_end": 1763930457104149184,
            "client_recv_start": 1763930457104148448,
            "client_trans_end": 1763930457104148160,
            "client_trans_start": 1763930457104147456,
            "server_recv_end": 1763930457104148256,
            "server_recv_start": 1763930457104147680,
            "server_trans_end": 1763930457104149184,
            "server_trans_start": 1763930457104148256
        },
        "pair15": {
            "client_recv_end": 1763930457104149184,
            "client_recv_start": 1763930457104148448,
            "client_trans_end": 1763930457104148160,
            "client_trans_start": 1763930457104147456,
            "server_recv_end": 1763930457104148256,
            "server_recv_start": 1763930457104147680,
            "server_trans_end": 1763930457104149184,
            "server_trans_start": 1763930457104148256
        },
        "pair2": {
            "client_recv_end": 1763930457104149184,
            "client_recv_start": 1763930457104148448,
            "client_trans_end": 1763930457104148160,
            "client_trans_start": 1763930457104147456,
            "server_recv_end": 1763930457104148256,
            "server_recv_start": 1763930457104147680,
            "server_trans_end": 1763930457104149184,
            "server_trans_start": 1763930457104148256
        },
        "pair3": {
            "client_recv_end": 1763930457104149184,
            "client_recv_start": 1763930457104148448,
            "client_trans_end": 1763930457104148160,
            "client_trans_start": 1763930457104147456,
            "server_recv_end": 1763930457104148256,
            "server_recv_start": 1763930457104147680,
            "server_trans_end": 1763930457104149184,
            "server_trans_start": 1763930457104148256
        },
        "pair4": {
            "client_recv_end": 1763930457104149184,
            "client_recv_start": 1763930457104148448,
            "client_trans_end": 1763930457104148160,
            "client_trans_start": 1763930457104147456,
            "server_recv_end": 1763930457104148256,
            "server_recv_start": 1763930457104147680,
            "server_trans_end": 1763930457104149184,
            "server_trans_start": 1763930457104148256
        },
        "pair5": {
            "client_recv_end": 1763930457104149184,
            "client_recv_start": 1763930457104148448,
            "client_trans_end": 1763930457104148160,
            "client_trans_start": 1763930457104147456,
            "server_recv_end": 1763930457104148256,
            "server_recv_start": 1763930457104147680,
            "server_trans_end": 1763930457104149184,
            "server_trans_start": 1763930457104148256
        },
        "pair6": {
            "client_recv_end": 1763930457104149184,
            "client_recv_start": 1763930457104148448,
            "client_trans_end": 1763930457104148160,
            "client_trans_start": 1763930457104147456,
            "server_recv_end": 1763930457104148256,
            "server_recv_start": 1763930457104147680,
            "server_trans_end": 1763930457104149184,
            "server_trans_start": 1763930457104148256
        },
        "pair7": {
            "client_recv_end": 1763930457104149184,
            "client_recv_start": 1763930457104148448,
            "client_trans_end": 1763930457104148160,
            "client_trans_start": 1763930457104147456,
            "server_recv_end": 1763930457104148256,
            "server_recv_start": 1763930457104147680,
            "server_trans_end": 1763930457104149184,
            "server_trans_start": 1763930457104148256
        },
        "pair8": {
            "client_recv_end": 1763930457104149184,
            "client_recv_start": 1763930457104148448,
            "client_trans_end": 1763930457104148160,
            "client_trans_start": 1763930457104147456,
            "server_recv_end": 1763930457104148256,
            "server_recv_start": 1763930457104147680,
            "server_trans_end": 1763930457104149184,
            "server_trans_start": 1763930457104148256
        },
        "pair9": {
            "client_recv_end": 1763930457104149184,
            "client_recv_start": 1763930457104148448,
            "client_trans_end": 1763930457104148160,
            "client_trans_start": 1763930457104147456,
            "server_recv_end": 1763930457104148256,
            "server_recv_start": 1763930457104147680,
            "server_trans_end": 1763930457104149184,
            "server_trans_start": 1763930457104148256
        }
    },
    "run1": {
        "pair0": {
            "client_recv_end": 1763930457104152640,
            "client_recv_start": 1763930457104152064,
            "client_trans_end": 1763930457104151776,
            "client_trans_start": 1763930457104151104,
            "server_recv_end": 1763930457104151776,
            "server_recv_start": 1763930457104151328,
            "server_trans_end": 1763930457104152672,
            "server_trans_start": 1763930457104151776
        },
        "pair1": {
            "client_recv_end": 1763930457104152640,
            "client_recv_start": 1763930457104152064,
            "client_trans_end": 1763930457104151776,
            "client_trans_start": 1763930457104151104,
            "server_recv_end": 1763930457104151776,
            "server_recv_start": 1763930457104151328,
            "server_trans_end": 1763930457104152672,
            "server_trans_start": 1763930457104151776
        },
        "pair10": {
            "client_recv_end": 1763930457104152640,
            "client_recv_start": 1763930457104152064,
            "client_trans_end": 1763930457104151776,
            "client_trans_start": 1763930457104151104,
            "server_recv_end": 1763930457104151776,
            "server_recv_start": 1763930457104151328,
            "server_trans_end": 1763930457104152672,
            "server_trans_start": 1763930457104151776
        },
        "pair11": {
            "client_recv_end": 1763930457104152640,
            "client_recv_start": 1763930457104152064,
            "client_trans_end": 1763930457104151776,
            "client_trans_start": 1763930457104151104,
            "server_recv_end": 1763930457104151776,
            "server_recv_start": 1763930457104151328,
            "server_trans_end": 1763930457104152672,
            "server_trans_start": 1763930457104151776
        },
        "pair12": {
            "client_recv_end": 1763930457104152640,
            "client_recv_start": 1763930457104152064,
            "client_trans_end": 1763930457104151776,
            "client_trans_start": 1763930457104151104,
            "server_recv_end": 1763930457104151776,
            "server_recv_start": 1763930457104151328,
            "server_trans_end": 1763930457104152672,
            "server_trans_start": 1763930457104151776
        },
        "pair13": {
            "client_recv_end": 1763930457104152640,
            "client_recv_start": 1763930457104152064,
            "client_trans_end": 1763930457104151776,
            "client_trans_start": 1763930457104151104,
            "server_recv_end": 1763930457104151776,
            "server_recv_start": 1763930457104151328,
            "server_trans_end": 1763930457104152672,
            "server_trans_start": 1763930457104151776
        },
        "pair14": {
            "client_recv_end": 1763930457104152640,
            "client_recv_start": 1763930457104152064,
            "client_trans_end": 1763930457104151776,
            "client_trans_start": 1763930457104151104,
            "server_recv_end": 1763930457104151776,
            "server_recv_start": 1763930457104151328,
            "server_trans_end": 1763930457104152672,
            "server_trans_start": 1763930457104151776
        },
        "pair15": {
            "client_recv_end": 1763930457104152640,
            "client_recv_start": 1763930457104152064,
            "client_trans_end": 1763930457104151776,
            "client_trans_start": 1763930457104151104,
            "server_recv_end": 1763930457104151776,
            "server_recv_start": 1763930457104151328,
            "server_trans_end": 1763930457104152672,
            "server_trans_start": 1763930457104151776
        },
        "pair2": {
            "client_recv_end": 1763930457104152640,
            "client_recv_start": 1763930457104152064,
            "client_trans_end": 1763930457104151776,
            "client_trans_start": 1763930457104151104,
            "server_recv_end": 1763930457104151776,
            "server_recv_start": 1763930457104151328,
            "server_trans_end": 1763930457104152672,
            "server_trans_start": 1763930457104151776
        },
        "pair3": {
            "client_recv_end": 1763930457104152640,
            "client_recv_start": 1763930457104152064,
            "client_trans_end": 1763930457104151776,
            "client_trans_start": 1763930457104151104,
            "server_recv_end": 1763930457104151776,
            "server_recv_start": 1763930457104151328,
            "server_trans_end": 1763930457104152672,
            "server_trans_start": 1763930457104151776
        },
        "pair4": {
            "client_recv_end": 1763930457104152640,
            "client_recv_start": 1763930457104152064,
            "client_trans_end": 1763930457104151776,
            "client_trans_start": 1763930457104151104,
            "server_recv_end": 1763930457104151776,
            "server_recv_start": 1763930457104151328,
            "server_trans_end": 1763930457104152672,
            "server_trans_start": 1763930457104151776
        },
        "pair5": {
            "client_recv_end": 1763930457104152640,
            "client_recv_start": 1763930457104152064,
            "client_trans_end": 1763930457104151776,
            "client_trans_start": 1763930457104151104,
            "server_recv_end": 1763930457104151776,
            "server_recv_start": 1763930457104151328,
            "server_trans_end": 1763930457104152672,
            "server_trans_start": 1763930457104151776
        },
        "pair6": {
            "client_recv_end": 1763930457104152640,
            "client_recv_start": 1763930457104152064,
            "client_trans_end": 1763930457104151776,
            "client_trans_start": 1763930457104151104,
            "server_recv_end": 1763930457104151776,
            "server_recv_start": 1763930457104151328,
            "server_trans_end": 1763930457104152672,
            "server_trans_start": 1763930457104151776
        },
        "pair7": {
            "client_recv_end": 1763930457104152640,
            "client_recv_start": 1763930457104152064,
            "client_trans_end": 1763930457104151776,
            "client_trans_start": 1763930457104151104,
            "server_recv_end": 1763930457104151776,
            "server_recv_start": 1763930457104151328,
            "server_trans_end": 1763930457104152672,
            "server_trans_start": 1763930457104151776
        },
        "pair8": {
            "client_recv_end": 1763930457104152640,
            "client_recv_start": 1763930457104152064,
            "client_trans_end": 1763930457104151776,
            "client_trans_start": 1763930457104151104,
            "server_recv_end": 1763930457104151776,
            "server_recv_start": 1763930457104151328,
            "server_trans_end": 1763930457104152672,
            "server_trans_start": 1763930457104151776
        },
        "pair9": {
            "client_recv_end": 1763930457104152640,
            "client_recv_start": 1763930457104152064,
            "client_trans_end": 1763930457104151776,
            "client_trans_start": 1763930457104151104,
            "server_recv_end": 1763930457104151776,
            "server_recv_start": 1763930457104151328,
            "server_trans_end": 1763930457104152672,
            "server_trans_start": 1763930457104151776
        }
    },
    "run2": {
        "pair0": {
            "client_recv_end": 1763930457104156224,
            "client_recv_start": 1763930457104155488,
            "client_trans_end": 1763930457104155200,
            "client_trans_start": 1763930457104154560,
            "server_recv_end": 1763930457104155296,
            "server_recv_start": 1763930457104154720,
            "server_trans_end": 1763930457104156192,
            "server_trans_start": 1763930457104155296
        },
        "pair1": {
            "client_recv_end": 1763930457104156224,
            "client_recv_start": 1763930457104155488,
            "client_trans_end": 1763930457104155200,
            "client_trans_start": 1763930457104154560,
            "server_recv_end": 1763930457104155296,
            "server_recv_start": 1763930457104154720,
            "server_trans_end": 1763930457104156192,
            "server_trans_start": 1763930457104155296
        },
        "pair10": {
            "client_recv_end": 1763930457104156224,
            "client_recv_start": 1763930457104155488,
            "client_trans_end": 1763930457104155200,
            "client_trans_start": 1763930457104154560,
            "server_recv_end": 1763930457104155296,
            "server_recv_start": 1763930457104154720,
            "server_trans_end": 1763930457104156192,
            "server_trans_start": 1763930457104155296
        },
        "pair11": {
            "client_recv_end": 1763930457104156224,
            "client_recv_start": 1763930457104155488,
            "client_trans_end": 1763930457104155200,
            "client_trans_start": 1763930457104154560,
            "server_recv_end": 1763930457104155296,
            "server_recv_start": 1763930457104154720,
            "server_trans_end": 1763930457104156192,
            "server_trans_start": 1763930457104155296
        },
        "pair12": {
            "client_recv_end": 1763930457104156224,
            "client_recv_start": 1763930457104155488,
            "client_trans_end": 1763930457104155200,
            "client_trans_start": 1763930457104154560,
            "server_recv_end": 1763930457104155296,
            "server_recv_start": 1763930457104154720,
            "server_trans_end": 1763930457104156192,
            "server_trans_start": 1763930457104155296
        },
        "pair13": {
            "client_recv_end": 1763930457104156224,
            "client_recv_start": 1763930457104155488,
            "client_trans_end": 1763930457104155200,
            "client_trans_start": 1763930457104154560,
            "server_recv_end": 1763930457104155296,
            "server_recv_start": 1763930457104154720,
            "server_trans_end": 1763930457104156192,
            "server_trans_start": 1763930457104155296
        },
        "pair14": {
            "client_recv_end": 1763930457104156224,
            "client_recv_start": 1763930457104155488,
            "client_trans_end": 1763930457104155200,
            "client_trans_start": 1763930457104154560,
            "server_recv_end": 1763930457104155296,
            "server_recv_start": 1763930457104154720,
            "server_trans_end": 1763930457104156192,
            "server_trans_start": 1763930457104155296
        },
        "pair15": {
            "client_recv_end": 1763930457104156224,
            "client_recv_start": 1763930457104155488,
            "client_trans_end": 1763930457104155200,
            "client_trans_start": 1763930457104154560,
            "server_recv_end": 1763930457104155296,
            "server_recv_start": 1763930457104154720,
            "server_trans_end": 1763930457104156192,
            "server_trans_start": 1763930457104155296
        },
        "pair2": {
            "client_recv_end": 1763930457104156224,
            "client_recv_start": 1763930457104155488,
            "client_trans_end": 1763930457104155200,
            "client_trans_start": 1763930457104154560,
            "server_recv_end": 1763930457104155296,
            "server_recv_start": 1763930457104154720,
            "server_trans_end": 1763930457104156192,
            "server_trans_start": 1763930457104155296
        },
        "pair3": {
            "client_recv_end": 1763930457104156224,
            "client_recv_start": 1763930457104155488,
            "client_trans_end": 1763930457104155200,
            "client_trans_start": 1763930457104154560,
            "server_recv_end": 1763930457104155296,
            "server_recv_start": 1763930457104154720,
            "server_trans_end": 1763930457104156192,
            "server_trans_start": 1763930457104155296
        },
        "pair4": {
            "client_recv_end": 1763930457104156224,
            "client_recv_start": 1763930457104155488,
            "client_trans_end": 1763930457104155200,
            "client_trans_start": 1763930457104154560,
            "server_recv_end": 1763930457104155296,
            "server_recv_start": 1763930457104154720,
            "server_trans_end": 1763930457104156192,
            "server_trans_start": 1763930457104155296
        },
        "pair5": {
            "client_recv_end": 1763930457104156224,
            "client_recv_start": 1763930457104155488,
            "client_trans_end": 1763930457104155200,
            "client_trans_start": 1763930457104154560,
            "server_recv_end": 1763930457104155296,
            "server_recv_start": 1763930457104154720,
            "server_trans_end": 1763930457104156192,
            "server_trans_start": 1763930457104155296
        },
        "pair6": {
            "client_recv_end": 1763930457104156224,
            "client_recv_start": 1763930457104155488,
            "client_trans_end": 1763930457104155200,
            "client_trans_start": 1763930457104154560,
            "server_recv_end": 1763930457104155296,
            "server_recv_start": 1763930457104154720,
            "server_trans_end": 1763930457104156192,
            "server_trans_start": 1763930457104155296
        },
        "pair7": {
            "client_recv_end": 1763930457104156224,
            "client_recv_start": 1763930457104155488,
            "client_trans_end": 1763930457104155200,
            "client_trans_start": 1763930457104154560,
            "server_recv_end": 1763930457104155296,
            "server_recv_start": 1763930457104154720,
            "server_trans_end": 1763930457104156192,
            "server_trans_start": 1763930457104155296
        },
        "pair8": {
            "client_recv_end": 1763930457104156224,
            "client_recv_start": 1763930457104155488,
            "client_trans_end": 1763930457104155200,
            "client_trans_start": 1763930457104154560,
            "server_recv_end": 1763930457104155296,
            "server_recv_start": 1763930457104154720,
            "server_trans_end": 1763930457104156192,
            "server_trans_start": 1763930457104155296
        },
        "pair9": {
            "client_recv_end": 1763930457104156224,
            "client_recv_start": 1763930457104155488,
            "client_trans_end": 1763930457104155200,
            "client_trans_start": 1763930457104154560,
            "server_recv_end": 1763930457104155296,
            "server_recv_start": 1763930457104154720,
            "server_trans_end": 1763930457104156192,
            "server_trans_start": 1763930457104155296
        }
    },
    "run3": {
        "pair0": {
            "client_recv_end": 1763930457104159648,
            "client_recv_start": 1763930457104159072,
            "client_trans_end": 1763930457104158784,
            "client_trans_start": 1763930457104158112,
            "server_recv_end": 1763930457104158784,
            "server_recv_start": 1763930457104158368,
            "server_trans_end": 1763930457104159680,
            "server_trans_start": 1763930457104158784
        },
        "pair1": {
            "client_recv_end": 1763930457104159648,
            "client_recv_start": 1763930457104159072,
            "client_trans_end": 1763930457104158784,
            "client_trans_start": 1763930457104158112,
            "server_recv_end": 1763930457104158784,
            "server_recv_start": 1763930457104158368,
            "server_trans_end": 1763930457104159680,
            "server_trans_start": 1763930457104158784
        },
        "pair10": {
            "client_recv_end": 1763930457104159648,
            "client_recv_start": 1763930457104159072,
            "client_trans_end": 1763930457104158784,
            "client_trans_start": 1763930457104158112,
            "server_recv_end": 1763930457104158784,
            "server_recv_start": 1763930457104158368,
            "server_trans_end": 1763930457104159680,
            "server_trans_start": 1763930457104158784
        },
        "pair11": {
            "client_recv_end": 1763930457104159648,
            "client_recv_start": 1763930457104159072,
            "client_trans_end": 1763930457104158784,
            "client_trans_start": 1763930457104158112,
            "server_recv_end": 1763930457104158784,
            "server_recv_start": 1763930457104158368,
            "server_trans_end": 1763930457104159680,
            "server_trans_start": 1763930457104158784
        },
        "pair12": {
            "client_recv_end": 1763930457104159648,
            "client_recv_start": 1763930457104159072,
            "client_trans_end": 1763930457104158784,
            "client_trans_start": 1763930457104158112,
            "server_recv_end": 1763930457104158784,
            "server_recv_start": 1763930457104158368,
            "server_trans_end": 1763930457104159680,
            "server_trans_start": 1763930457104158784
        },
        "pair13": {
            "client_recv_end": 1763930457104159648,
            "client_recv_start": 1763930457104159072,
            "client_trans_end": 1763930457104158784,
            "client_trans_start": 1763930457104158112,
            "server_recv_end": 1763930457104158784,
            "server_recv_start": 1763930457104158368,
            "server_trans_end": 1763930457104159680,
            "server_trans_start": 1763930457104158784
        },
        "pair14": {
            "client_recv_end": 1763930457104159648,
            "client_recv_start": 1763930457104159072,
            "client_trans_end": 1763930457104158784,
            "client_trans_start": 1763930457104158112,
            "server_recv_end": 1763930457104158784,
            "server_recv_start": 1763930457104158368,
            "server_trans_end": 1763930457104159680,
            "server_trans_start": 1763930457104158784
        },
        "pair15": {
            "client_recv_end": 1763930457104159648,
            "client_recv_start": 1763930457104159072,
            "client_trans_end": 1763930457104158784,
            "client_trans_start": 1763930457104158112,
            "server_recv_end": 1763930457104158784,
            "server_recv_start": 1763930457104158368,
            "server_trans_end": 1763930457104159680,
            "server_trans_start": 1763930457104158784
        },
        "pair2": {
            "client_recv_end": 1763930457104159648,
            "client_recv_start": 1763930457104159072,
            "client_trans_end": 1763930457104158784,
            "client_trans_start": 1763930457104158112,
            "server_recv_end": 1763930457104158784,
            "server_recv_start": 1763930457104158368,
            "server_trans_end": 1763930457104159680,
            "server_trans_start": 1763930457104158784
        },
        "pair3": {
            "client_recv_end": 1763930457104159648,
            "client_recv_start": 1763930457104159072,
            "client_trans_end": 1763930457104158784,
            "client_trans_start": 1763930457104158112,
            "server_recv_end": 1763930457104158784,
            "server_recv_start": 1763930457104158368,
            "server_trans_end": 1763930457104159680,
            "server_trans_start": 1763930457104158784
        },
        "pair4": {
            "client_recv_end": 1763930457104159648,
            "client_recv_start": 1763930457104159072,
            "client_trans_end": 1763930457104158784,
            "client_trans_start": 1763930457104158112,
            "server_recv_end": 1763930457104158784,
            "server_recv_start": 1763930457104158368,
            "server_trans_end": 1763930457104159680,
            "server_trans_start": 1763930457104158784
        },
        "pair5": {
            "client_recv_end": 1763930457104159648,
            "client_recv_start": 1763930457104159072,
            "client_trans_end": 1763930457104158784,
            "client_trans_start": 1763930457104158112,
            "server_recv_end": 1763930457104158784,
            "server_recv_start": 1763930457104158368,
            "server_trans_end": 1763930457104159680,
            "server_trans_start": 1763930457104158784
        },
        "pair6": {
            "client_recv_end": 1763930457104159648,
            "client_recv_start": 1763930457104159072,
            "client_trans_end": 1763930457104158784,
            "client_trans_start": 1763930457104158112,
            "server_recv_end": 1763930457104158784,
            "server_recv_start": 1763930457104158368,
            "server_trans_end": 1763930457104159680,
            "server_trans_start": 1763930457104158784
        },
        "pair7": {
            "client_recv_end": 1763930457104159648,
            "client_recv_start": 1763930457104159072,
            "client_trans_end": 1763930457104158784,
            "client_trans_start": 1763930457104158112,
            "server_recv_end": 1763930457104158784,
            "server_recv_start": 1763930457104158368,
            "server_trans_end": 1763930457104159680,
            "server_trans_start": 1763930457104158784
        },
        "pair8": {
            "client_recv_end": 1763930457104159648,
            "client_recv_start": 1763930457104159072,
            "client_trans_end": 1763930457104158784,
            "client_trans_start": 1763930457104158112,
            "server_recv_end": 1763930457104158784,
            "server_recv_start": 1763930457104158368,
            "server_trans_end": 1763930457104159680,
            "server_trans_start": 1763930457104158784
        },
        "pair9": {
            "client_recv_end": 1763930457104159648,
            "client_recv_start": 1763930457104159072,
            "client_trans_end": 1763930457104158784,
            "client_trans_start": 1763930457104158112,
            "server_recv_end": 1763930457104158784,
            "server_recv_start": 1763930457104158368,
            "server_trans_end": 1763930457104159680,
            "server_trans_start": 1763930457104158784
        }
    },
    "run4": {
        "pair0": {
            "client_recv_end": 1763930457104163232,
            "client_recv_start": 1763930457104162496,
            "client_trans_end": 1763930457104162208,
            "client_trans_start": 1763930457104161536,
            "server_recv_end": 1763930457104162304,
            "server_recv_start": 1763930457104161728,
            "server_trans_end": 1763930457104163200,
            "server_trans_start": 1763930457104162304
        },
        "pair1": {
            "client_recv_end": 1763930457104163232,
            "client_recv_start": 1763930457104162496,
            "client_trans_end": 1763930457104162208,
            "client_trans_start": 1763930457104161536,
            "server_recv_end": 1763930457104162304,
            "server_recv_start": 1763930457104161728,
            "server_trans_end": 1763930457104163200,
            "server_trans_start": 1763930457104162304
        },
        "pair10": {
            "client_recv_end": 1763930457104163232,
            "client_recv_start": 1763930457104162496,
            "client_trans_end": 1763930457104162208,
            "client_trans_start": 1763930457104161536,
            "server_recv_end": 1763930457104162304,
            "server_recv_start": 1763930457104161728,
            "server_trans_end": 1763930457104163200,
            "server_trans_start": 1763930457104162304
        },
        "pair11": {
            "client_recv_end": 1763930457104163232,
            "client_recv_start": 1763930457104162496,
            "client_trans_end": 1763930457104162208,
            "client_trans_start": 1763930457104161536,
            "server_recv_end": 1763930457104162304,
            "server_recv_start": 1763930457104161728,
            "server_trans_end": 1763930457104163200,
            "server_trans_start": 1763930457104162304
        },
        "pair12": {
            "client_recv_end": 1763930457104163232,
            "client_recv_start": 1763930457104162496,
            "client_trans_end": 1763930457104162208,
            "client_trans_start": 1763930457104161536,
            "server_recv_end": 1763930457104162304,
            "server_recv_start": 1763930457104161728,
            "server_trans_end": 1763930457104163200,
            "server_trans_start": 1763930457104162304
        },
        "pair13": {
            "client_recv_end": 1763930457104163232,
            "client_recv_start": 1763930457104162496,
            "client_trans_end": 1763930457104162208,
            "client_trans_start": 1763930457104161536,
            "server_recv_end": 1763930457104162304,
            "server_recv_start": 1763930457104161728,
            "server_trans_end": 1763930457104163200,
            "server_trans_start": 1763930457104162304
        },
        "pair14": {
            "client_recv_end": 1763930457104163232,
            "client_recv_start": 1763930457104162496,
            "client_trans_end": 1763930457104162208,
            "client_trans_start": 1763930457104161536,
            "server_recv_end": 1763930457104162304,
            "server_recv_start": 1763930457104161728,
            "server_trans_end": 1763930457104163200,
            "server_trans_start": 1763930457104162304
        },
        "pair15": {
            "client_recv_end": 1763930457104163232,
            "client_recv_start": 1763930457104162496,
            "client_trans_end": 1763930457104162208,
            "client_trans_start": 1763930457104161536,
            "server_recv_end": 1763930457104162304,
            "server_recv_start": 1763930457104161728,
            "server_trans_end": 1763930457104163200,
            "server_trans_start": 1763930457104162304
        },
        "pair2": {
            "client_recv_end": 1763930457104163232,
            "client_recv_start": 1763930457104162496,
            "client_trans_end": 1763930457104162208,
            "client_trans_start": 1763930457104161536,
            "server_recv_end": 1763930457104162304,
            "server_recv_start": 1763930457104161728,
            "server_trans_end": 1763930457104163200,
            "server_trans_start": 1763930457104162304
        },
        "pair3": {
            "client_recv_end": 1763930457104163232,
            "client_recv_start": 1763930457104162496,
            "client_trans_end": 1763930457104162208,
            "client_trans_start": 1763930457104161536,
            "server_recv_end": 1763930457104162304,
            "server_recv_start": 1763930457104161728,
            "server_trans_end": 1763930457104163200,
            "server_trans_start": 1763930457104162304
        },
        "pair4": {
            "client_recv_end": 1763930457104163232,
            "client_recv_start": 1763930457104162496,
            "client_trans_end": 1763930457104162208,
            "client_trans_start": 1763930457104161536,
            "server_recv_end": 1763930457104162304,
            "server_recv_start": 1763930457104161728,
            "server_trans_end": 1763930457104163200,
            "server_trans_start": 1763930457104162304
        },
        "pair5": {
            "client_recv_end": 1763930457104163232,
            "client_recv_start": 1763930457104162496,
            "client_trans_end": 1763930457104162208,
            "client_trans_start": 1763930457104161536,
            "server_recv_end": 1763930457104162304,
            "server_recv_start": 1763930457104161728,
            "server_trans_end": 1763930457104163200,
            "server_trans_start": 1763930457104162304
        },
        "pair6": {
            "client_recv_end": 1763930457104163232,
            "client_recv_start": 1763930457104162496,
            "client_trans_end": 1763930457104162208,
            "client_trans_start": 1763930457104161536,
            "server_recv_end": 1763930457104162304,
            "server_recv_start": 1763930457104161728,
            "server_trans_end": 1763930457104163200,
            "server_trans_start": 1763930457104162304
        },
        "pair7": {
            "client_recv_end": 1763930457104163232,
            "client_recv_start": 1763930457104162496,
            "client_trans_end": 1763930457104162208,
            "client_trans_start": 1763930457104161536,
            "server_recv_end": 1763930457104162304,
            "server_recv_start": 1763930457104161728,
            "server_trans_end": 1763930457104163200,
            "server_trans_start": 1763930457104162304
        },
        "pair8": {
            "client_recv_end": 1763930457104163232,
            "client_recv_start": 1763930457104162496,
            "client_trans_end": 1763930457104162208,
            "client_trans_start": 1763930457104161536,
            "server_recv_end": 1763930457104162304,
            "server_recv_start": 1763930457104161728,
            "server_trans_end": 1763930457104163200,
            "server_trans_start": 1763930457104162304
        },
        "pair9": {
            "client_recv_end": 1763930457104163232,
            "client_recv_start": 1763930457104162496,
            "client_trans_end": 1763930457104162208,
            "client_trans_start": 1763930457104161536,
            "server_recv_end": 1763930457104162304,
            "server_recv_start": 1763930457104161728,
            "server_trans_end": 1763930457104163200,
            "server_trans_start": 1763930457104162304
        }
    },
    "run5": {
        "pair0": {
            "client_recv_end": 1763930457104166656,
            "client_recv_start": 1763930457104166080,
            "client_trans_end": 1763930457104165792,
            "client_trans_start": 1763930457104165120,
            "server_recv_end": 1763930457104165792,
            "server_recv_start": 1763930457104165376,
            "server_trans_end": 1763930457104166720,
            "server_trans_start": 1763930457104165792
        },
        "pair1": {
            "client_recv_end": 1763930457104166656,
            "client_recv_start": 1763930457104166080,
            "client_trans_end": 1763930457104165792,
            "client_trans_start": 1763930457104165120,
            "server_recv_end": 1763930457104165792,
            "server_recv_start": 1763930457104165376,
            "server_trans_end": 1763930457104166720,
            "server_trans_start": 1763930457104165792
        },
        "pair10": {
            "client_recv_end": 1763930457104166656,
            "client_recv_start": 1763930457104166080,
            "client_trans_end": 1763930457104165792,
            "client_trans_start": 1763930457104165120,
            "server_recv_end": 1763930457104165792,
            "server_recv_start": 1763930457104165376,
            "server_trans_end": 1763930457104166720,
            "server_trans_start": 1763930457104165792
        },
        "pair11": {
            "client_recv_end": 1763930457104166656,
            "client_recv_start": 1763930457104166080,
            "client_trans_end": 1763930457104165792,
            "client_trans_start": 1763930457104165120,
            "server_recv_end": 1763930457104165792,
            "server_recv_start": 1763930457104165376,
            "server_trans_end": 1763930457104166720,
            "server_trans_start": 1763930457104165792
        },
        "pair12": {
            "client_recv_end": 1763930457104166656,
            "client_recv_start": 1763930457104166080,
            "client_trans_end": 1763930457104165792,
            "client_trans_start": 1763930457104165120,
            "server_recv_end": 1763930457104165792,
            "server_recv_start": 1763930457104165376,
            "server_trans_end": 1763930457104166720,
            "server_trans_start": 1763930457104165792
        },
        "pair13": {
            "client_recv_end": 1763930457104166656,
            "client_recv_start": 1763930457104166080,
            "client_trans_end": 1763930457104165792,
            "client_trans_start": 1763930457104165120,
            "server_recv_end": 1763930457104165792,
            "server_recv_start": 1763930457104165376,
            "server_trans_end": 1763930457104166720,
            "server_trans_start": 1763930457104165792
        },
        "pair14": {
            "client_recv_end": 1763930457104166656,
            "client_recv_start": 1763930457104166080,
            "client_trans_end": 1763930457104165792,
            "client_trans_start": 1763930457104165120,
            "server_recv_end": 1763930457104165792,
            "server_recv_start": 1763930457104165376,
            "server_trans_end": 1763930457104166720,
            "server_trans_start": 1763930457104165792
        },
        "pair15": {
            "client_recv_end": 1763930457104166656,
            "client_recv_start": 1763930457104166080,
            "client_trans_end": 1763930457104165792,
            "client_trans_start": 1763930457104165120,
            "server_recv_end": 1763930457104165792,
            "server_recv_start": 1763930457104165376,
            "server_trans_end": 1763930457104166720,
            "server_trans_start": 1763930457104165792
        },
        "pair2": {
            "client_recv_end": 1763930457104166656,
            "client_recv_start": 1763930457104166080,
            "client_trans_end": 1763930457104165792,
            "client_trans_start": 1763930457104165120,
            "server_recv_end": 1763930457104165792,
            "server_recv_start": 1763930457104165376,
            "server_trans_end": 1763930457104166720,
            "server_trans_start": 1763930457104165792
        },
        "pair3": {
            "client_recv_end": 1763930457104166656,
            "client_recv_start": 1763930457104166080,
            "client_trans_end": 1763930457104165792,
            "client_trans_start": 1763930457104165120,
            "server_recv_end": 1763930457104165792,
            "server_recv_start": 1763930457104165376,
            "server_trans_end": 1763930457104166720,
            "server_trans_start": 1763930457104165792
        },
        "pair4": {
            "client_recv_end": 1763930457104166656,
            "client_recv_start": 1763930457104166080,
            "client_trans_end": 1763930457104165792,
            "client_trans_start": 1763930457104165120,
            "server_recv_end": 1763930457104165792,
            "server_recv_start": 1763930457104165376,
            "server_trans_end": 1763930457104166720,
            "server_trans_start": 1763930457104165792
        },
        "pair5": {
            "client_recv_end": 1763930457104166656,
            "client_recv_start": 1763930457104166080,
            "client_trans_end": 1763930457104165792,
            "client_trans_start": 1763930457104165120,
            "server_recv_end": 1763930457104165792,
            "server_recv_start": 1763930457104165376,
            "server_trans_end": 1763930457104166720,
            "server_trans_start": 1763930457104165792
        },
        "pair6": {
            "client_recv_end": 1763930457104166656,
            "client_recv_start": 1763930457104166080,
            "client_trans_end": 1763930457104165792,
            "client_trans_start": 1763930457104165120,
            "server_recv_end": 1763930457104165792,
            "server_recv_start": 1763930457104165376,
            "server_trans_end": 1763930457104166720,
            "server_trans_start": 1763930457104165792
        },
        "pair7": {
            "client_recv_end": 1763930457104166656,
            "client_recv_start": 1763930457104166080,
            "client_trans_end": 1763930457104165792,
            "client_trans_start": 1763930457104165120,
            "server_recv_end": 1763930457104165792,
            "server_recv_start": 1763930457104165376,
            "server_trans_end": 1763930457104166720,
            "server_trans_start": 1763930457104165792
        },
        "pair8": {
            "client_recv_end": 1763930457104166656,
            "client_recv_start": 1763930457104166080,
            "client_trans_end": 1763930457104165792,
            "client_trans_start": 1763930457104165120,
            "server_recv_end": 1763930457104165792,
            "server_recv_start": 1763930457104165376,
            "server_trans_end": 1763930457104166720,
            "server_trans_start": 1763930457104165792
        },
        "pair9": {
            "client_recv_end": 1763930457104166656,
            "client_recv_start": 1763930457104166080,
            "client_trans_end": 1763930457104165792,
            "client_trans_start": 1763930457104165120,
            "server_recv_end": 1763930457104165792,
            "server_recv_start": 1763930457104165376,
            "server_trans_end": 1763930457104166720,
            "server_trans_start": 1763930457104165792
        }
    },
    "run6": {
        "pair0": {
            "client_recv_end": 1763930457104170112,
            "client_recv_start": 1763930457104169376,
            "client_trans_end": 1763930457104169216,
            "client_trans_start": 1763930457104168576,
            "server_recv_end": 1763930457104169184,
            "server_recv_start": 1763930457104168736,
            "server_trans_end": 1763930457104170080,
            "server_trans_start": 1763930457104169184
        },
        "pair1": {
            "client_recv_end": 1763930457104170112,
            "client_recv_start": 1763930457104169376,
            "client_trans_end": 1763930457104169216,
            "client_trans_start": 1763930457104168576,
            "server_recv_end": 1763930457104169184,
            "server_recv_start": 1763930457104168736,
            "server_trans_end": 1763930457104170080,
            "server_trans_start": 1763930457104169184
        },
        "pair10": {
            "client_recv_end": 1763930457104170112,
            "client_recv_start": 1763930457104169376,
            "client_trans_end": 1763930457104169216,
            "client_trans_start": 1763930457104168576,
            "server_recv_end": 1763930457104169184,
            "server_recv_start": 1763930457104168736,
            "server_trans_end": 1763930457104170080,
            "server_trans_start": 1763930457104169184
        },
        "pair11": {
            "client_recv_end": 1763930457104170112,
            "client_recv_start": 1763930457104169376,
            "client_trans_end": 1763930457104169216,
            "client_trans_start": 1763930457104168576,
            "server_recv_end": 1763930457104169184,
            "server_recv_start": 1763930457104168736,
            "server_trans_end": 1763930457104170080,
            "server_trans_start": 1763930457104169184
        },
        "pair12": {
            "client_recv_end": 1763930457104170112,
            "client_recv_start": 1763930457104169376,
            "client_trans_end": 1763930457104169216,
            "client_trans_start": 1763930457104168576,
            "server_recv_end": 1763930457104169184,
            "server_recv_start": 1763930457104168736,
            "server_trans_end": 1763930457104170080,
            "server_trans_start": 1763930457104169184
        },
        "pair13": {
            "client_recv_end": 1763930457104170112,
            "client_recv_start": 1763930457104169376,
            "client_trans_end": 1763930457104169216,
            "client_trans_start": 1763930457104168576,
            "server_recv_end": 1763930457104169184,
            "server_recv_start": 1763930457104168736,
            "server_trans_end": 1763930457104170080,
            "server_trans_start": 1763930457104169184
        },
        "pair14": {
            "client_recv_end": 1763930457104170112,
            "client_recv_start": 1763930457104169376,
            "client_trans_end": 1763930457104169216,
            "client_trans_start": 1763930457104168576,
            "server_recv_end": 1763930457104169184,
            "server_recv_start": 1763930457104168736,
            "server_trans_end": 1763930457104170080,
            "server_trans_start": 1763930457104169184
        },
        "pair15": {
            "client_recv_end": 1763930457104170112,
            "client_recv_start": 1763930457104169376,
            "client_trans_end": 1763930457104169216,
            "client_trans_start": 1763930457104168576,
            "server_recv_end": 1763930457104169184,
            "server_recv_start": 1763930457104168736,
            "server_trans_end": 1763930457104170080,
            "server_trans_start": 1763930457104169184
        },
        "pair2": {
            "client_recv_end": 1763930457104170112,
            "client_recv_start": 1763930457104169376,
            "client_trans_end": 1763930457104169216,
            "client_trans_start": 1763930457104168576,
            "server_recv_end": 1763930457104169184,
            "server_recv_start": 1763930457104168736,
            "server_trans_end": 1763930457104170080,
            "server_trans_start": 1763930457104169184
        },
        "pair3": {
            "client_recv_end": 1763930457104170112,
            "client_recv_start": 1763930457104169376,
            "client_trans_end": 1763930457104169216,
            "client_trans_start": 1763930457104168576,
            "server_recv_end": 1763930457104169184,
            "server_recv_start": 1763930457104168736,
            "server_trans_end": 1763930457104170080,
            "server_trans_start": 1763930457104169184
        },
        "pair4": {
            "client_recv_end": 1763930457104170112,
            "client_recv_start": 1763930457104169376,
            "client_trans_end": 1763930457104169216,
            "client_trans_start": 1763930457104168576,
            "server_recv_end": 1763930457104169184,
            "server_recv_start": 1763930457104168736,
            "server_trans_end": 1763930457104170080,
            "server_trans_start": 1763930457104169184
        },
        "pair5": {
            "client_recv_end": 1763930457104170112,
            "client_recv_start": 1763930457104169376,
            "client_trans_end": 1763930457104169216,
            "client_trans_start": 1763930457104168576,
            "server_recv_end": 1763930457104169184,
            "server_recv_start": 1763930457104168736,
            "server_trans_end": 1763930457104170080,
            "server_trans_start": 1763930457104169184
        },
        "pair6": {
            "client_recv_end": 1763930457104170112,
            "client_recv_start": 1763930457104169376,
            "client_trans_end": 1763930457104169216,
            "client_trans_start": 1763930457104168576,
            "server_recv_end": 1763930457104169184,
            "server_recv_start": 1763930457104168736,
            "server_trans_end": 1763930457104170080,
            "server_trans_start": 1763930457104169184
        },
        "pair7": {
            "client_recv_end": 1763930457104170112,
            "client_recv_start": 1763930457104169376,
            "client_trans_end": 1763930457104169216,
            "client_trans_start": 1763930457104168576,
            "server_recv_end": 1763930457104169184,
            "server_recv_start": 1763930457104168736,
            "server_trans_end": 1763930457104170080,
            "server_trans_start": 1763930457104169184
        },
        "pair8": {
            "client_recv_end": 1763930457104170112,
            "client_recv_start": 1763930457104169376,
            "client_trans_end": 1763930457104169216,
            "client_trans_start": 1763930457104168576,
            "server_recv_end": 1763930457104169184,
            "server_recv_start": 1763930457104168736,
            "server_trans_end": 1763930457104170080,
            "server_trans_start": 1763930457104169184
        },
        "pair9": {
            "client_recv_end": 1763930457104170112,
            "client_recv_start": 1763930457104169376,
            "client_trans_end": 1763930457104169216,
            "client_trans_start": 1763930457104168576,
            "server_recv_end": 1763930457104169184,
            "server_recv_start": 1763930457104168736,
            "server_trans_end": 1763930457104170080,
            "server_trans_start": 1763930457104169184
        }
    },
    "run7": {
        "pair0": {
            "client_recv_end": 1763930457104173696,
            "client_recv_start": 1763930457104172960,
            "client_trans_end": 1763930457104172672,
            "client_trans_start": 1763930457104172000,
            "server_recv_end": 1763930457104172704,
            "server_recv_start": 1763930457104172256,
            "server_trans_end": 1763930457104173600,
            "server_trans_start": 1763930457104172704
        },
        "pair1": {
            "client_recv_end": 1763930457104173696,
            "client_recv_start": 1763930457104172960,
            "client_trans_end": 1763930457104172672,
            "client_trans_start": 1763930457104172000,
            "server_recv_end": 1763930457104172704,
            "server_recv_start": 1763930457104172256,
            "server_trans_end": 1763930457104173600,
            "server_trans_start": 1763930457104172704
        },
        "pair10": {
            "client_recv_end": 1763930457104173696,
            "client_recv_start": 1763930457104172960,
            "client_trans_end": 1763930457104172672,
            "client_trans_start": 1763930457104172000,
            "server_recv_end": 1763930457104172704,
            "server_recv_start": 1763930457104172256,
            "server_trans_end": 1763930457104173600,
            "server_trans_start": 1763930457104172704
        },
        "pair11": {
            "client_recv_end": 1763930457104173696,
            "client_recv_start": 1763930457104172960,
            "client_trans_end": 1763930457104172672,
            "client_trans_start": 1763930457104172000,
            "server_recv_end": 1763930457104172704,
            "server_recv_start": 1763930457104172256,
            "server_trans_end": 1763930457104173600,
            "server_trans_start": 1763930457104172704
        },
        "pair12": {
            "client_recv_end": 1763930457104173696,
            "client_recv_start": 1763930457104172960,
            "client_trans_end": 1763930457104172672,
            "client_trans_start": 1763930457104172000,
            "server_recv_end": 1763930457104172704,
            "server_recv_start": 1763930457104172256,
            "server_trans_end": 1763930457104173600,
            "server_trans_start": 1763930457104172704
        },
        "pair13": {
            "client_recv_end": 1763930457104173696,
            "client_recv_start": 1763930457104172960,
            "client_trans_end": 1763930457104172672,
            "client_trans_start": 1763930457104172000,
            "server_recv_end": 1763930457104172704,
            "server_recv_start": 1763930457104172256,
            "server_trans_end": 1763930457104173600,
            "server_trans_start": 1763930457104172704
        },
        "pair14": {
            "client_recv_end": 1763930457104173696,
            "client_recv_start": 1763930457104172960,
            "client_trans_end": 1763930457104172672,
            "client_trans_start": 1763930457104172000,
            "server_recv_end": 1763930457104172704,
            "server_recv_start": 1763930457104172256,
            "server_trans_end": 1763930457104173600,
            "server_trans_start": 1763930457104172704
        },
        "pair15": {
            "client_recv_end": 1763930457104173696,
            "client_recv_start": 1763930457104172960,
            "client_trans_end": 1763930457104172672,
            "client_trans_start": 1763930457104172000,
            "server_recv_end": 1763930457104172704,
            "server_recv_start": 1763930457104172256,
            "server_trans_end": 1763930457104173600,
            "server_trans_start": 1763930457104172704
        },
        "pair2": {
            "client_recv_end": 1763930457104173696,
            "client_recv_start": 1763930457104172960,
            "client_trans_end": 1763930457104172672,
            "client_trans_start": 1763930457104172000,
            "server_recv_end": 1763930457104172704,
            "server_recv_start": 1763930457104172256,
            "server_trans_end": 1763930457104173600,
            "server_trans_start": 1763930457104172704
        },
        "pair3": {
            "client_recv_end": 1763930457104173696,
            "client_recv_start": 1763930457104172960,
            "client_trans_end": 1763930457104172672,
            "client_trans_start": 1763930457104172000,
            "server_recv_end": 1763930457104172704,
            "server_recv_start": 1763930457104172256,
            "server_trans_end": 1763930457104173600,
            "server_trans_start": 1763930457104172704
        },
        "pair4": {
            "client_recv_end": 1763930457104173696,
            "client_recv_start": 1763930457104172960,
            "client_trans_end": 1763930457104172672,
            "client_trans_start": 1763930457104172000,
            "server_recv_end": 1763930457104172704,
            "server_recv_start": 1763930457104172256,
            "server_trans_end": 1763930457104173600,
            "server_trans_start": 1763930457104172704
        },
        "pair5": {
            "client_recv_end": 1763930457104173696,
            "client_recv_start": 1763930457104172960,
            "client_trans_end": 1763930457104172672,
            "client_trans_start": 1763930457104172000,
            "server_recv_end": 1763930457104172704,
            "server_recv_start": 1763930457104172256,
            "server_trans_end": 1763930457104173600,
            "server_trans_start": 1763930457104172704
        },
        "pair6": {
            "client_recv_end": 1763930457104173696,
            "client_recv_start": 1763930457104172960,
            "client_trans_end": 1763930457104172672,
            "client_trans_start": 1763930457104172000,
            "server_recv_end": 1763930457104172704,
            "server_recv_start": 1763930457104172256,
            "server_trans_end": 1763930457104173600,
            "server_trans_start": 1763930457104172704
        },
        "pair7": {
            "client_recv_end": 1763930457104173696,
            "client_recv_start": 1763930457104172960,
            "client_trans_end": 1763930457104172672,
            "client_trans_start": 1763930457104172000,
            "server_recv_end": 1763930457104172704,
            "server_recv_start": 1763930457104172256,
            "server_trans_end": 1763930457104173600,
            "server_trans_start": 1763930457104172704
        },
        "pair8": {
            "client_recv_end": 1763930457104173696,
            "client_recv_start": 1763930457104172960,
            "client_trans_end": 1763930457104172672,
            "client_trans_start": 1763930457104172000,
            "server_recv_end": 1763930457104172704,
            "server_recv_start": 1763930457104172256,
            "server_trans_end": 1763930457104173600,
            "server_trans_start": 1763930457104172704
        },
        "pair9": {
            "client_recv_end": 1763930457104173696,
            "client_recv_start": 1763930457104172960,
            "client_trans_end": 1763930457104172672,
            "client_trans_start": 1763930457104172000,
            "server_recv_end": 1763930457104172704,
            "server_recv_start": 1763930457104172256,
            "server_trans_end": 1763930457104173600,
            "server_trans_start": 1763930457104172704
        }
    },
    "run8": {
        "pair0": {
            "client_recv_end": 1763930457104177120,
            "client_recv_start": 1763930457104176384,
            "client_trans_end": 1763930457104176256,
            "client_trans_start": 1763930457104175584,
            "server_recv_end": 1763930457104176192,
            "server_recv_start": 1763930457104175776,
            "server_trans_end": 1763930457104177088,
            "server_trans_start": 1763930457104176192
        },
        "pair1": {
            "client_recv_end": 1763930457104177120,
            "client_recv_start": 1763930457104176384,
            "client_trans_end": 1763930457104176256,
            "client_trans_start": 1763930457104175584,
            "server_recv_end": 1763930457104176192,
            "server_recv_start": 1763930457104175776,
            "server_trans_end": 1763930457104177088,
            "server_trans_start": 1763930457104176192
        },
        "pair10": {
            "client_recv_end": 1763930457104177120,
            "client_recv_start": 1763930457104176384,
            "client_trans_end": 1763930457104176256,
            "client_trans_start": 1763930457104175584,
            "server_recv_end": 1763930457104176192,
            "server_recv_start": 1763930457104175776,
            "server_trans_end": 1763930457104177088,
            "server_trans_start": 1763930457104176192
        },
        "pair11": {
            "client_recv_end": 1763930457104177120,
            "client_recv_start": 1763930457104176384,
            "client_trans_end": 1763930457104176256,
            "client_trans_start": 1763930457104175584,
            "server_recv_end": 1763930457104176192,
            "server_recv_start": 1763930457104175776,
            "server_trans_end": 1763930457104177088,
            "server_trans_start": 1763930457104176192
        },
        "pair12": {
            "client_recv_end": 1763930457104177120,
            "client_recv_start": 1763930457104176384,
            "client_trans_end": 1763930457104176256,
            "client_trans_start": 1763930457104175584,
            "server_recv_end": 1763930457104176192,
            "server_recv_start": 1763930457104175776,
            "server_trans_end": 1763930457104177088,
            "server_trans_start": 1763930457104176192
        },
        "pair13": {
            "client_recv_end": 1763930457104177120,
            "client_recv_start": 1763930457104176384,
            "client_trans_end": 1763930457104176256,
            "client_trans_start": 1763930457104175584,
            "server_recv_end": 1763930457104176192,
            "server_recv_start": 1763930457104175776,
            "server_trans_end": 1763930457104177088,
            "server_trans_start": 1763930457104176192
        },
        "pair14": {
            "client_recv_end": 1763930457104177120,
            "client_recv_start": 1763930457104176384,
            "client_trans_end": 1763930457104176256,
            "client_trans_start": 1763930457104175584,
            "server_recv_end": 1763930457104176192,
            "server_recv_start": 1763930457104175776,
            "server_trans_end": 1763930457104177088,
            "server_trans_start": 1763930457104176192
        },
        "pair15": {
            "client_recv_end": 1763930457104177120,
            "client_recv_start": 1763930457104176384,
            "client_trans_end": 1763930457104176256,
            "client_trans_start": 1763930457104175584,
            "server_recv_end": 1763930457104176192,
            "server_recv_start": 1763930457104175776,
            "server_trans_end": 1763930457104177088,
            "server_trans_start": 1763930457104176192
        },
        "pair2": {
            "client_recv_end": 1763930457104177120,
            "client_recv_start": 1763930457104176384,
            "client_trans_end": 1763930457104176256,
            "client_trans_start": 1763930457104175584,
            "server_recv_end": 1763930457104176192,
            "server_recv_start": 1763930457104175776,
            "server_trans_end": 1763930457104177088,
            "server_trans_start": 1763930457104176192
        },
        "pair3": {
            "client_recv_end": 1763930457104177120,
            "client_recv_start": 1763930457104176384,
            "client_trans_end": 1763930457104176256,
            "client_trans_start": 1763930457104175584,
            "server_recv_end": 1763930457104176192,
            "server_recv_start": 1763930457104175776,
            "server_trans_end": 1763930457104177088,
            "server_trans_start": 1763930457104176192
        },
        "pair4": {
            "client_recv_end": 1763930457104177120,
            "client_recv_start": 1763930457104176384,
            "client_trans_end": 1763930457104176256,
            "client_trans_start": 1763930457104175584,
            "server_recv_end": 1763930457104176192,
            "server_recv_start": 1763930457104175776,
            "server_trans_end": 1763930457104177088,
            "server_trans_start": 1763930457104176192
        },
        "pair5": {
            "client_recv_end": 1763930457104177120,
            "client_recv_start": 1763930457104176384,
            "client_trans_end": 1763930457104176256,
            "client_trans_start": 1763930457104175584,
            "server_recv_end": 1763930457104176192,
            "server_recv_start": 1763930457104175776,
            "server_trans_end": 1763930457104177088,
            "server_trans_start": 1763930457104176192
        },
        "pair6": {
            "client_recv_end": 1763930457104177120,
            "client_recv_start": 1763930457104176384,
            "client_trans_end": 1763930457104176256,
            "client_trans_start": 1763930457104175584,
            "server_recv_end": 1763930457104176192,
            "server_recv_start": 1763930457104175776,
            "server_trans_end": 1763930457104177088,
            "server_trans_start": 1763930457104176192
        },
        "pair7": {
            "client_recv_end": 1763930457104177120,
            "client_recv_start": 1763930457104176384,
            "client_trans_end": 1763930457104176256,
            "client_trans_start": 1763930457104175584,
            "server_recv_end": 1763930457104176192,
            "server_recv_start": 1763930457104175776,
            "server_trans_end": 1763930457104177088,
            "server_trans_start": 1763930457104176192
        },
        "pair8": {
            "client_recv_end": 1763930457104177120,
            "client_recv_start": 1763930457104176384,
            "client_trans_end": 1763930457104176256,
            "client_trans_start": 1763930457104175584,
            "server_recv_end": 1763930457104176192,
            "server_recv_start": 1763930457104175776,
            "server_trans_end": 1763930457104177088,
            "server_trans_start": 1763930457104176192
        },
        "pair9": {
            "client_recv_end": 1763930457104177120,
            "client_recv_start": 1763930457104176384,
            "client_trans_end": 1763930457104176256,
            "client_trans_start": 1763930457104175584,
            "server_recv_end": 1763930457104176192,
            "server_recv_start": 1763930457104175776,
            "server_trans_end": 1763930457104177088,
            "server_trans_start": 1763930457104176192
        }
    },
    "run9": {
        "pair0": {
            "client_recv_end": 1763930457104180704,
            "client_recv_start": 1763930457104179968,
            "client_trans_end": 1763930457104179680,
            "client_trans_start": 1763930457104179008,
            "server_recv_end": 1763930457104179712,
            "server_recv_start": 1763930457104179264,
            "server_trans_end": 1763930457104180608,
            "server_trans_start": 1763930457104179712
        },
        "pair1": {
            "client_recv_end": 1763930457104180704,
            "client_recv_start": 1763930457104179968,
            "client_trans_end": 1763930457104179680,
            "client_trans_start": 1763930457104179008,
            "server_recv_end": 1763930457104179712,
            "server_recv_start": 1763930457104179264,
            "server_trans_end": 1763930457104180608,
            "server_trans_start": 1763930457104179712
        },
        "pair10": {
            "client_recv_end": 1763930457104180704,
            "client_recv_start": 1763930457104179968,
            "client_trans_end": 1763930457104179680,
            "client_trans_start": 1763930457104179008,
            "server_recv_end": 1763930457104179712,
            "server_recv_start": 1763930457104179264,
            "server_trans_end": 1763930457104180608,
            "server_trans_start": 1763930457104179712
        },
        "pair11": {
            "client_recv_end": 1763930457104180704,
            "client_recv_start": 1763930457104179968,
            "client_trans_end": 1763930457104179680,
            "client_trans_start": 1763930457104179008,
            "server_recv_end": 1763930457104179712,
            "server_recv_start": 1763930457104179264,
            "server_trans_end": 1763930457104180608,
            "server_trans_start": 1763930457104179712
        },
        "pair12": {
            "client_recv_end": 1763930457104180704,
            "client_recv_start": 1763930457104179968,
            "client_trans_end": 1763930457104179680,
            "client_trans_start": 1763930457104179008,
            "server_recv_end": 1763930457104179712,
            "server_recv_start": 1763930457104179264,
            "server_trans_end": 1763930457104180608,
            "server_trans_start": 1763930457104179712
        },
        "pair13": {
            "client_recv_end": 1763930457104180704,
            "client_recv_start": 1763930457104179968,
            "client_trans_end": 1763930457104179680,
            "client_trans_start": 1763930457104179008,
            "server_recv_end": 1763930457104179712,
            "server_recv_start": 1763930457104179264,
            "server_trans_end": 1763930457104180608,
            "server_trans_start": 1763930457104179712
        },
        "pair14": {
            "client_recv_end": 1763930457104180704,
            "client_recv_start": 1763930457104179968,
            "client_trans_end": 1763930457104179680,
            "client_trans_start": 1763930457104179008,
            "server_recv_end": 1763930457104179712,
            "server_recv_start": 1763930457104179264,
            "server_trans_end": 1763930457104180608,
            "server_trans_start": 1763930457104179712
        },
        "pair15": {
            "client_recv_end": 1763930457104180704,
            "client_recv_start": 1763930457104179968,
            "client_trans_end": 1763930457104179680,
            "client_trans_start": 1763930457104179008,
            "server_recv_end": 1763930457104179712,
            "server_recv_start": 1763930457104179264,
            "server_trans_end": 1763930457104180608,
            "server_trans_start": 1763930457104179712
        },
        "pair2": {
            "client_recv_end": 1763930457104180704,
            "client_recv_start": 1763930457104179968,
            "client_trans_end": 1763930457104179680,
            "client_trans_start": 1763930457104179008,
            "server_recv_end": 1763930457104179712,
            "server_recv_start": 1763930457104179264,
            "server_trans_end": 1763930457104180608,
            "server_trans_start": 1763930457104179712
        },
        "pair3": {
            "client_recv_end": 1763930457104180704,
            "client_recv_start": 1763930457104179968,
            "client_trans_end": 1763930457104179680,
            "client_trans_start": 1763930457104179008,
            "server_recv_end": 1763930457104179712,
            "server_recv_start": 1763930457104179264,
            "server_trans_end": 1763930457104180608,
            "server_trans_start": 1763930457104179712
        },
        "pair4": {
            "client_recv_end": 1763930457104180704,
            "client_recv_start": 1763930457104179968,
            "client_trans_end": 1763930457104179680,
            "client_trans_start": 1763930457104179008,
            "server_recv_end": 1763930457104179712,
            "server_recv_start": 1763930457104179264,
            "server_trans_end": 1763930457104180608,
            "server_trans_start": 1763930457104179712
        },
        "pair5": {
            "client_recv_end": 1763930457104180704,
            "client_recv_start": 1763930457104179968,
            "client_trans_end": 1763930457104179680,
            "client_trans_start": 1763930457104179008,
            "server_recv_end": 1763930457104179712,
            "server_recv_start": 1763930457104179264,
            "server_trans_end": 1763930457104180608,
            "server_trans_start": 1763930457104179712
        },
        "pair6": {
            "client_recv_end": 1763930457104180704,
            "client_recv_start": 1763930457104179968,
            "client_trans_end": 1763930457104179680,
            "client_trans_start": 1763930457104179008,
            "server_recv_end": 1763930457104179712,
            "server_recv_start": 1763930457104179264,
            "server_trans_end": 1763930457104180608,
            "server_trans_start": 1763930457104179712
        },
        "pair7": {
            "client_recv_end": 1763930457104180704,
            "client_recv_start": 1763930457104179968,
            "client_trans_end": 1763930457104179680,
            "client_trans_start": 1763930457104179008,
            "server_recv_end": 1763930457104179712,
            "server_recv_start": 1763930457104179264,
            "server_trans_end": 1763930457104180608,
            "server_trans_start": 1763930457104179712
        },
        "pair8": {
            "client_recv_end": 1763930457104180704,
            "client_recv_start": 1763930457104179968,
            "client_trans_end": 1763930457104179680,
            "client_trans_start": 1763930457104179008,
            "server_recv_end": 1763930457104179712,
            "server_recv_start": 1763930457104179264,
            "server_trans_end": 1763930457104180608,
            "server_trans_start": 1763930457104179712
        },
        "pair9": {
            "client_recv_end": 1763930457104180704,
            "client_recv_start": 1763930457104179968,
            "client_trans_end": 1763930457104179680,
            "client_trans_start": 1763930457104179008,
            "server_recv_end": 1763930457104179712,
            "server_recv_start": 1763930457104179264,
            "server_trans_end": 1763930457104180608,
            "server_trans_start": 1763930457104179712
        }
    }
}