{
    "message_size": 64,
    "n_runs": 10,
    "num_pairs": 2,
    "run0": {
        "pair0": {
            "client_recv_end": 1764463920704609280,
            "client_recv_start": 1764463920704607232,
            "client_trans_end": 1764463920704607232,
            "client_trans_start": 1764463920704606208,
            "server_recv_end": 1764463920704607232,
            "server_recv_start": 1764463920704606208,
            "server_trans_end": 1764463920704609280,
            "server_trans_start": 1764463920704607232
        },
        "pair1": {
            "client_recv_end": 1764463920704609280,
            "client_recv_start": 1764463920704607232,
            "client_trans_end": 1764463920704607232,
            "client_trans_start": 1764463920704606208,
            "server_recv_end": 1764463920704607232,
            "server_recv_start": 1764463920704606208,
            "server_trans_end": 1764463920704609280,
            "server_trans_start": 1764463920704607232
        }
    },
    "run1": {
        "pair0": {
            "client_recv_end": 1764463920704616448,
            "client_recv_start": 1764463920704614400,
            "client_trans_end": 1764463920704613376,
            "client_trans_start": 1764463920704612352,
            "server_recv_end": 1764463920704613376,
            "server_recv_start": 1764463920704613376,
            "server_trans_end": 1764463920704615424,
            "server_trans_start": 1764463920704613376
        },
        "pair1": {
            "client_recv_end": 1764463920704616448,
            "client_recv_start": 1764463920704614400,
            "client_trans_end": 1764463920704613376,
            "client_trans_start": 1764463920704612352,
            "server_recv_end": 1764463920704613376,
            "server_recv_start": 1764463920704613376,
            "server_trans_end": 1764463920704615424,
            "server_trans_start": 1764463920704613376
        }
    },
    "run2": {
        "pair0": {
            "client_recv_end": 1764463920704622592,
            "client_recv_start": 1764463920704620544,
            "client_trans_end": 1764463920704620544,
            "client_trans_start": 1764463920704619520,
            "server_recv_end": 1764463920704620544,
            "server_recv_start": 1764463920704619520,
            "server_trans_end": 1764463920704622592,
            "server_trans_start": 1764463920704620544
        },
        "pair1": {
            "client_recv_end": 1764463920704622592,
            "client_recv_start": 1764463920704620544,
            "client_trans_end": 1764463920704620544,
            "client_trans_start": 1764463920704619520,
            "server_recv_end": 1764463920704620544,
            "server_recv_start": 1764463920704619520,
            "server_trans_end": 1764463920704622592,
            "server_trans_start": 1764463920704620544
        }
    },
    "run3": {
        "pair0": {
            "client_recv_end": 1764463920704629760,
            "client_recv_start": 1764463920704627712,
            "client_trans_end": 1764463920704627712,
            "client_trans_start": 1764463920704626688,
            "server_recv_end": 1764463920704627712,
            "server_recv_start": 1764463920704626688,
            "server_trans_end": 1764463920704629760,
            "server_trans_start": 1764463920704627712
        },
        "pair1": {
            "client_recv_end": 1764463920704629760,
            "client_recv_start": 1764463920704627712,
            "client_trans_end": 1764463920704627712,
            "client_trans_start": 1764463920704626688,
            "server_recv_end": 1764463920704627712,
            "server_recv_start": 1764463920704626688,
            "server_trans_end": 1764463920704629760,
            "server_trans_start": 1764463920704627712
        }
    },
    "run4": {
        "pair0": {
            "client_recv_end": 1764463920704635904,
            "client_recv_start": 1764463920704633856,
            "client_trans_end": 1764463920704633856,
            "client_trans_start": 1764463920704632832,
            "server_recv_end": 1764463920704633856,
            "server_recv_start": 1764463920704633856,
            "server_trans_end": 1764463920704635904,
            "server_trans_start": 1764463920704633856
        },
        "pair1": {
            "client_recv_end": 1764463920704635904,
            "client_recv_start": 1764463920704633856,
            "client_trans_end": 1764463920704633856,
            "client_trans_start": 1764463920704632832,
            "server_recv_end": 1764463920704633856,
            "server_recv_start": 1764463920704633856,
            "server_trans_end": 1764463920704635904,
            "server_trans_start": 1764463920704633856
        }
    },
    "run5": {
        "pair0": {
            "client_recv_end": 1764463920704643072,
            "client_recv_start": 1764463920704641024,
            "client_trans_end": 1764463920704641024,
            "client_trans_start": 1764463920704640000,
            "server_recv_end": 1764463920704641024,
            "server_recv_start": 1764463920704640000,
            "server_trans_end": 1764463920704643072,
            "server_trans_start": 1764463920704641024
        },
        "pair1": {
            "client_recv_end": 1764463920704643072,
            "client_recv_start": 1764463920704641024,
            "client_trans_end": 1764463920704641024,
            "client_trans_start": 1764463920704640000,
            "server_recv_end": 1764463920704641024,
            "server_recv_start": 1764463920704640000,
            "server_trans_end": 1764463920704643072,
            "server_trans_start": 1764463920704641024
        }
    },
    "run6": {
        "pair0": {
            "client_recv_end": 1764463920704650240,
            "client_recv_start": 1764463920704648192,
            "client_trans_end": 1764463920704648192,
            "client_trans_start": 1764463920704646144,
            "server_recv_end": 1764463920704648192,
            "server_recv_start": 1764463920704647168,
            "server_trans_end": 1764463920704650240,
            "server_trans_start": 1764463920704648192
        },
        "pair1": {
            "client_recv_end": 1764463920704650240,
            "client_recv_start": 1764463920704648192,
            "client_trans_end": 1764463920704648192,
            "client_trans_start": 1764463920704646144,
            "server_recv_end": 1764463920704648192,
            "server_recv_start": 1764463920704647168,
            "server_trans_end": 1764463920704650240,
            "server_trans_start": 1764463920704648192
        }
    },
    "run7": {
        "pair0": {
            "client_recv_end": 1764463920704656384,
            "client_recv_start": 1764463920704655360,
            "client_trans_end": 1764463920704654336,
            "client_trans_start": 1764463920704653312,
            "server_recv_end": 1764463920704654336,
            "server_recv_start": 1764463920704653312,
            "server_trans_end": 1764463920704656384,
            "server_trans_start": 1764463920704654336
        },
        "pair1": {
            "client_recv_end": 1764463920704656384,
            "client_recv_start": 1764463920704655360,
            "client_trans_end": 1764463920704654336,
            "client_trans_start": 1764463920704653312,
            "server_recv_end": 1764463920704654336,
            "server_recv_start": 1764463920704653312,
            "server_trans_end": 1764463920704656384,
            "server_trans_start": 1764463920704654336
        }
    },
    "run8": {
        "pair0": {
            "client_recv_end": 1764463920704663552,
            "client_recv_start": 1764463920704661504,
            "client_trans_end": 1764463920704661504,
            "client_trans_start": 1764463920704660480,
            "server_recv_end": 1764463920704661504,
            "server_recv_start": 1764463920704660480,
            "server_trans_end": 1764463920704663552,
            "server_trans_start": 1764463920704661504
        },
        "pair1": {
            "client_recv_end": 1764463920704663552,
            "client_recv_start": 1764463920704661504,
            "client_trans_end": 1764463920704661504,
            "client_trans_start": 1764463920704660480,
            "server_recv_end": 1764463920704661504,
            "server_recv_start": 1764463920704660480,
            "server_trans_end": 1764463920704663552,
            "server_trans_start": 1764463920704661504
        }
    },
    "run9": {
        "pair0": {
            "client_recv_end": 1764463920704670720,
            "client_recv_start": 1764463920704668672,
            "client_trans_end": 1764463920704668672,
            "client_trans_start": 1764463920704667648,
            "server_recv_end": 1764463920704668672,
            "server_recv_start": 1764463920704667648,
            "server_trans_end": 1764463920704670720,
            "server_trans_start": 1764463920704668672
        },
        "pair1": {
            "client_recv_end": 1764463920704670720,
            "client_recv_start": 1764463920704668672,
            "client_trans_end": 1764463920704668672,
            "client_trans_start": 1764463920704667648,
            "server_recv_end": 1764463920704668672,
            "server_recv_start": 1764463920704667648,
            "server_trans_end": 1764463920704670720,
            "server_trans_start": 1764463920704668672
        }
    }
}